<?xml version="1.0" encoding="utf-8" ?><dwsync><file name="example.php" server="173.201.216.41" local="3362277738" remote="11953581092" /><file name="example.xml" server="173.201.216.41" local="3362277738" remote="11953581092" /><file name="gmail.php" server="173.201.216.41" local="3362277738" remote="11953581092" /><file name="gmail.xml" server="173.201.216.41" local="3362277738" remote="11953581092" /><file name="index.html" server="173.201.216.41" local="3362277738" remote="11953581092" /><file name="joomla.php" server="173.201.216.41" local="3362277738" remote="11953581092" /><file name="joomla.xml" server="173.201.216.41" local="3362277738" remote="11953581092" /><file name="ldap.php" server="173.201.216.41" local="3362277738" remote="11953581092" /><file name="ldap.xml" server="173.201.216.41" local="3362277738" remote="11953581092" /><file name="openid.php" server="173.201.216.41" local="3362277738" remote="11953581092" /><file name="openid.xml" server="173.201.216.41" local="3362277738" remote="11953581092" /></dwsync>