<?xml version="1.0" encoding="utf-8" ?><dwsync><file name="attachmentlibrary.php" server="173.201.216.41" local="3362277738" remote="11953581452" /><file name="cms-directory-xhtml-entities.xml" server="173.201.216.41" local="3362277738" remote="11953581452" /><file name="cms-directory-xhtml-latin1.xml" server="173.201.216.41" local="3362277738" remote="11953581452" /><file name="cms-directory-xhtml-special.xml" server="173.201.216.41" local="3362277738" remote="11953581452" /><file name="cms-directory-xhtml-symbol.xml" server="173.201.216.41" local="3362277738" remote="11953581452" /><file name="directory.php" server="173.201.216.41" local="3363725602" remote="11953660172" /><file name="imagelibrary.php" server="173.201.216.41" local="3362277738" remote="11953581452" /><file name="index.html" server="173.201.216.41" local="3362277738" remote="11953581452" /><file name="preview.xsl" server="173.201.216.41" local="3362277738" remote="11953581452" /><file name="xstandard.js" server="173.201.216.41" local="3362277738" remote="11953581452" /></dwsync>